postcoder
