Metadata-Version: 1.0
Name: PostCoder
Version: 0.1.1
Summary: A simple API in python to work with       postcoder, a popular web service for addresses &       postcodes in the UK       
Home-page: http://www.openlabs.co.in
Author: Sharoon Thomas
Author-email: sharoon.thomas@openlabs.co.in
License: MIT
Keywords: postcoder UK postcodes
Platform: UNKNOWN
Classifier: Development Status :: 4 - Beta
Classifier: Environment :: Web Environment
Classifier: Intended Audience :: Developers
Classifier: Programming Language :: Python
